morphenepython/__init__.py
morphenepython/account.py
morphenepython/aes.py
morphenepython/amount.py
morphenepython/asciichart.py
morphenepython/asset.py
morphenepython/block.py
morphenepython/blockchain.py
morphenepython/blockchainobject.py
morphenepython/cli.py
morphenepython/constants.py
morphenepython/exceptions.py
morphenepython/instance.py
morphenepython/memo.py
morphenepython/message.py
morphenepython/morphene.py
morphenepython/nodelist.py
morphenepython/notify.py
morphenepython/profile.py
morphenepython/rc.py
morphenepython/snapshot.py
morphenepython/storage.py
morphenepython/transactionbuilder.py
morphenepython/utils.py
morphenepython/version.py
morphenepython/wallet.py
morphenepython/witness.py
morphenepythonapi/__init__.py
morphenepythonapi/exceptions.py
morphenepythonapi/graphenerpc.py
morphenepythonapi/morphenenoderpc.py
morphenepythonapi/node.py
morphenepythonapi/rpcutils.py
morphenepythonapi/version.py
morphenepythonapi/websocket.py
morphenepythonbase/__init__.py
morphenepythonbase/memo.py
morphenepythonbase/objects.py
morphenepythonbase/objecttypes.py
morphenepythonbase/operationids.py
morphenepythonbase/operations.py
morphenepythonbase/signedtransactions.py
morphenepythonbase/transactions.py
morphenepythonbase/version.py
morphenepythongrapheneapi/__init__.py
morphenepythongraphenebase/__init__.py
morphenepythongraphenebase/account.py
morphenepythongraphenebase/base58.py
morphenepythongraphenebase/bip38.py
morphenepythongraphenebase/chains.py
morphenepythongraphenebase/dictionary.py
morphenepythongraphenebase/ecdsasig.py
morphenepythongraphenebase/objects.py
morphenepythongraphenebase/objecttypes.py
morphenepythongraphenebase/operationids.py
morphenepythongraphenebase/operations.py
morphenepythongraphenebase/py23.py
morphenepythongraphenebase/signedtransactions.py
morphenepythongraphenebase/types.py
morphenepythongraphenebase/version.py
morphenepython-0.1.8.dist-info/LICENSE.txt
morphenepython-0.1.8.dist-info/METADATA
morphenepython-0.1.8.dist-info/WHEEL
morphenepython-0.1.8.dist-info/entry_points.txt
morphenepython-0.1.8.dist-info/top_level.txt
morphenepython-0.1.8.dist-info/RECORD
